<DOMSymbolItem xmlns:xsi="http://www.w3.org/2001/XMLSchema-instance" xmlns="http://ns.adobe.com/xfl/2008/" name="Shapes/Shape 1243" itemID="591c88da-00000775" symbolType="graphic" lastModified="1495042266">
  <timeline>
    <DOMTimeline name="Shape 1243">
      <layers>
        <DOMLayer name="Shape Sublayer 1" color="#4F80FF" current="true" isSelected="true">
          <frames>
            <DOMFrame index="0" keyMode="8704">
              <elements>
                <DOMShape isFloating="true">
                  <fills>
                    <FillStyle index="1">
                      <SolidColor/>
                    </FillStyle>
                    <FillStyle index="2">
                      <SolidColor color="#FFEB33"/>
                    </FillStyle>
                    <FillStyle index="3">
                      <SolidColor color="#EDE2D1"/>
                    </FillStyle>
                    <FillStyle index="4">
                      <SolidColor color="#347FB5"/>
                    </FillStyle>
                    <FillStyle index="5">
                      <SolidColor color="#F7F4AE"/>
                    </FillStyle>
                    <FillStyle index="6">
                      <SolidColor color="#A3FFA3"/>
                    </FillStyle>
                    <FillStyle index="7">
                      <SolidColor color="#C38A6D"/>
                    </FillStyle>
                    <FillStyle index="8">
                      <SolidColor color="#C2DDF2"/>
                    </FillStyle>
                    <FillStyle index="9">
                      <SolidColor color="#8B5C29"/>
                    </FillStyle>
                  </fills>
                  <edges>
                    <Edge fillStyle0="1" fillStyle1="2" edges="!7 -3325|12 -3346!12 -3346|34 -3400!34 -3400[58 -3438 93 -3450!93 -3450[107 -3454 109 -3470!109 -3470[111 -3485 99 -3485!99 -3485|90 -3484!90 -3484[10 -3454 -23 -3345!-23 -3345[-189 -3450 -392 -3395!-392 -3395[-595 -3340 -684 -3166!-684
 -3166[-732 -3173 -786 -3211!-786 -3211[-826 -3241 -844 -3264!-844 -3264[-806 -3267 -761 -3287!-761 -3287[-753 -3290 -749 -3299!-749 -3299[-742 -3307 -746 -3316!-746 -3316[-781 -3392 -791 -3467!-791 -3467|-739 -3442!-739 -3442[-728 -3438
 -719 -3447!-719 -3447[-709 -3457 -709 -3467!-709 -3467[-708 -3547 -640 -3595!-640 -3595[-659 -3540 -651 -3483!-651 -3483[-650 -3472 -639 -3472!-639 -3472[-628 -3472 -623 -3481!-623 -3481[-576 -3534 -540 -3546!-540 -3546[-587 -3482 -552
 -3414!-552 -3414[-548 -3407 -538 -3409!-538 -3409[-529 -3410 -524 -3416!-524 -3416[-496 -3450 -443 -3462!-443 -3462|-354 -3486!-354 -3486[-331 -3498 -273 -3562!-273 -3562[-224 -3615 -183 -3618!-183 -3618[-150 -3620 -104 -3592!-104 -3592
|-38 -3542!-38 -3542|-27 -3533!-27 -3533|-14 -3530!-14 -3530[63 -3548 113 -3532!113 -3532[148 -3519 166 -3493!166 -3493[170 -3487 178 -3490!178 -3490[213 -3501 236 -3528!236 -3528[241 -3484 223 -3433!223 -3433[219 -3427 221 -3421!221
 -3421[224 -3414 232 -3414!232 -3414[288 -3412 341 -3392!341 -3392|291 -3373!291 -3373[282 -3370 276 -3358!276 -3358[271 -3345 282 -3339!282 -3339[384 -3282 427 -3225!427 -3225[394 -3231 356 -3225!356 -3225|340 -3214!340 -3214[333 -3204
 336 -3195!336 -3195[384 -3099 391 -3022!391 -3022[398 -2948 369 -2856!369 -2856|369 -2857!369 -2857|348 -2801!348 -2801[336 -2890 273 -2957!273 -2957|216 -3011!216 -3011|174 -3042!174 -3042|172 -3130!172 -3130[166 -3182 148 -3213!148
 -3213[143 -3222 134 -3218!134 -3218[124 -3216 118 -3208"/>
                    <Edge fillStyle0="1" edges="
!27 -3572|-1 -3568!-1 -3568|-22 -3584!-22 -3584[-90 -3640 -141 -3649!-141 -3649[-193 -3659 -241 -3627!-241 -3627|-319 -3554!-319 -3554[-346 -3528 -392 -3518!-392 -3518|-472 -3499!-472 -3499[-496 -3488 -525 -3459!-525 -3459[-542 -3511
 -489 -3557!-489 -3557[-482 -3564 -482 -3574!-482 -3574[-482 -3585 -493 -3586!-493 -3586[-555 -3592 -617 -3530!-617 -3530[-617 -3582 -590 -3627!-590 -3627[-584 -3638 -589 -3646!-589 -3646[-594 -3655 -606 -3649!-606 -3649[-660 -3626 -695
 -3585!-695 -3585[-732 -3542 -742 -3488!-742 -3488[-782 -3507 -797 -3525!-797 -3525|-818 -3523!-818 -3523[-830 -3513 -830 -3502!-830 -3502[-830 -3410 -789 -3310!-789 -3310|-874 -3302!-874 -3302[-884 -3304 -895 -3292!-895 -3292[-904 -3281
 -899 -3271!-899 -3271[-866 -3219 -829 -3187!-829 -3187|-805 -3170!-805 -3170[-836 -3083 -813 -3030!-813 -3030|-813 -3029!-813 -3029|-787 -2981!-787 -2981|-820 -2895!-820 -2895[-877 -2725 -845 -2548!-845 -2548[-812 -2368 -699 -2242!-699
 -2242|-653 -2197!-653 -2197[-734 -2149 -793 -2086!-793 -2086[-859 -2016 -888 -1938!-888 -1938[-931 -1820 -895 -1620!-895 -1620[-869 -1488 -794 -1392!-794 -1392[-764 -1275 -752 -1200!-752 -1200[-734 -1094 -735 -1004!-735 -1004[-735 -985
 -745 -918!-745 -918[-752 -856 -734 -833!-734 -833[-764 -604 -739 -323!-739 -323[-720 -115 -662 180!-662 180[-625 369 -579 545!-579 545|-578 545!-578 545|-566 594!-566 594|-567 594!-567 594|-566 598!-566 598|-517 768!-517 768[-606 825
 -685 892!-685 892[-742 941 -764 978!-764 978[-800 1035 -777 1087!-777 1087[-750 1148 -651 1148!-651 1148|-501 1126!-501 1126[-360 1096 -299 1038!-299 1038|-193 927!-193 927[-165 966 -108 951!-108 951[-53 935 -30 889!-30 889[8 815 -69
 678!-69 678|-55 598!-55 598|-54 594!-54 594|-55 594!-55 594|-47 545!-47 545|-46 545!-46 545[-32 438 -32 350!-32 350|-32 347!-32 347[85 470 229 541!229 541|228 549!228 549|220 598!220 598[202 728 224 813!224 813[248 906 297 911!297 911
[359 918 430 869!430 869[488 829 531 768!531 768[580 701 602 598!602 598|612 549!612 549|617 501!617 501[624 431 615 403!615 403|593 361!593 361|585 344!585 344|599 337!599 337[628 329 626 296!626 296|609 239!609 239[592 192 556 158!556
 158[527 131 476 103!476 103[454 -148 370 -257!370 -257[424 -441 426 -713!426 -713|416 -741!416 -741|451 -833!451 -833[466 -887 479 -1001!479 -1001|484 -1077!484 -1077[489 -1123 503 -1151!503 -1151[536 -1203 546 -1234!546 -1234|557 -1290
!557 -1290|563 -1347!563 -1347[579 -1434 581 -1551!581 -1551[583 -1782 522 -1951!522 -1951[495 -2020 440 -2075!440 -2075[399 -2116 321 -2167!321 -2167[191 -2251 92 -2266!92 -2266[176 -2350 210 -2402!210 -2402[297 -2388 354 -2488!354 -2488
[413 -2589 342 -2665!342 -2665|351 -2675!351 -2675|380 -2732!380 -2732[440 -2846 445 -2963!445 -2963[449 -3088 388 -3191!388 -3191[426 -3189 456 -3169!456 -3169[468 -3161 480 -3172!480 -3172[491 -3183 488 -3196!488 -3196[464 -3279 335
 -3356!335 -3356[367 -3368 401 -3364!401 -3364[415 -3363 424 -3378!424 -3378[433 -3393 420 -3400!420 -3400[343 -3445 252 -3450!252 -3450[278 -3450 274 -3511!274 -3511[272 -3556 263 -3585!263 -3585[258 -3596 245 -3590!245 -3590[232 -3584
 229 -3574!229 -3574[211 -3528 187 -3538!187 -3538[154 -3561 130 -3569!130 -3569|27 -3572"/>
                    <Edge fillStyle0="2" fillStyle1="1" edges="
!41 -3318|54 -3342!54 -3342|91 -3384!91 -3384[115 -3404 125 -3404!125 -3404[140 -3403 119 -3375!119 -3375|82 -3325!82 -3325[72 -3307 65 -3283!65 -3283|62 -3276!83 -3273|91 -3285!91 -3285|92 -3288!92 -3288[110 -3310 128 -3316!128 -3316
[148 -3321 153 -3305!153 -3305[157 -3289 141 -3286!141 -3286[129 -3283 117 -3262!117 -3262|105 -3241!105 -3241[101 -3231 90 -3231"/>
                    <Edge fillStyle0="2" fillStyle1="3" edges="
!7 -3325|41 -3318"/>
                    <Edge fillStyle0="1" fillStyle1="3" edges="
!118 -3208[108 -3198 115 -3189!115 -3189[130 -3161 136 -3114!136 -3114|138 -3032!138 -3032|180 -3004!180 -3004[229 -2975 252 -2945!252 -2945[329 -2846 326 -2762!326 -2762[299 -2841 248 -2904!248 -2904[187 -2975 166 -2983!166 -2983[153
 -2989 146 -2979!146 -2979[140 -2971 151 -2963!151 -2963|177 -2941!177 -2941|229 -2888!229 -2888[273 -2840 319 -2740!319 -2740|311 -2720!311 -2720[279 -2796 233 -2847!233 -2847[198 -2885 165 -2901!165 -2901[154 -2905 151 -2892!151 -2892
[147 -2878 163 -2869!163 -2869[196 -2848 214 -2827!214 -2827[244 -2793 303 -2697!303 -2697|299 -2690!299 -2690|281 -2686!281 -2686[265 -2678 276 -2660!276 -2660[353 -2597 306 -2510!306 -2510[260 -2423 163 -2439!163 -2439[62 -2274 -81
 -2189!-81 -2189[-119 -2168 -75 -2169!-75 -2169[-30 -2171 24 -2205!24 -2205[8 -2106 -135 -2046!-135 -2046[-274 -1988 -339 -2036!-339 -2036[-323 -2031 -269 -2045!-269 -2045[-215 -2059 -218 -2067!-218 -2067[-241 -2065 -284 -2066!-284 -2066
[-375 -2068 -485 -2123!-485 -2123[-518 -2138 -556 -2166!-556 -2166[-617 -2211 -663 -2267!-663 -2267[-759 -2386 -792 -2548!-792 -2548[-825 -2708 -787 -2861!-787 -2861[-765 -2941 -707 -3054!-707 -3054[-618 -3227 -513 -3303!-513 -3303[-403
 -3380 -248 -3371!-248 -3371[-113 -3361 -28 -3299!-28 -3299[-20 -3292 -10 -3299!-10 -3299|4 -3315!4 -3315|7 -3325!41 -3318|36 -3310!36 -3310|23 -3269!23 -3269[20 -3259 33 -3253!33 -3253[46 -3247 54 -3260!54 -3260|59 -3267!59 -3267|62
 -3276"/>
                    <Edge fillStyle0="2" fillStyle1="3" edges="
!62 -3276|83 -3273"/>
                    <Edge fillStyle0="1" fillStyle1="3" edges="
!83 -3273|81 -3267!81 -3267|77 -3260!77 -3260|74 -3251!74 -3251[72 -3243 78 -3236!78 -3236[83 -3231 90 -3231"/>
                    <Edge fillStyle0="2" fillStyle1="3" edges="
!90 -3231|118 -3208"/>
                    <Edge fillStyle0="1" fillStyle1="3" edges="
!218 -2752|192 -2788!192 -2788[171 -2813 141 -2827!141 -2827[132 -2831 126 -2820!126 -2820[120 -2810 134 -2799!134 -2799|175 -2771!175 -2771|208 -2733!208 -2733[225 -2712 228 -2723!228 -2723[230 -2731 218 -2752!143 -2744[133 -2750 126
 -2740!126 -2740[121 -2728 130 -2723!130 -2723|144 -2710!144 -2710[159 -2695 159 -2686!159 -2686[160 -2674 173 -2674!173 -2674[185 -2675 184 -2691!184 -2691[183 -2708 169 -2724!169 -2724|143 -2744"/>
                    <Edge fillStyle0="1" fillStyle1="5" edges="
!140 -2211[179 -2099 108 -2000!108 -2000[47 -1913 -69 -1870!-69 -1870|-123 -1861!-123 -1861[-158 -1856 -171 -1843!-171 -1843[-189 -1826 -202 -1780!-202 -1780[-231 -1671 -228 -1515!-228 -1515|-209 -1247!-209 -1247[-198 -1110 -177 -1005
!-177 -1005|-166 -946!-166 -946[-154 -905 -135 -896!-135 -896[-122 -891 -90 -896!-90 -896|-43 -906!-43 -906|7 -914!7 -914|11 -919!11 -919[-32 -832 -75 -772!-75 -772[-113 -717 -155 -696!-155 -696|-195 -690!-195 -690|-239 -689!-239 -689
[-521 -699 -709 -852!-709 -852|-721 -880!-721 -880[-716 -951 -718 -1023!-718 -1023[-682 -984 -626 -954!-626 -954|-555 -929!-555 -929[-497 -915 -490 -940!-490 -940[-484 -966 -487 -1004!-487 -1004|-495 -1069!-495 -1069|-523 -1354!-523 -1354
[-524 -1429 -502 -1542!-502 -1542|-465 -1727!-465 -1727[-454 -1793 -468 -1857!-468 -1857|-522 -1976!-522 -1976[-556 -2049 -534 -2099!-534 -2099|-535 -2116!-535 -2116[-507 -2101 -489 -2095!-489 -2095[-423 -1946 -221 -1974!-221 -1974[-23
 -2002 56 -2152!56 -2152[79 -2194 83 -2237!83 -2237|138 -2226!138 -2226|140 -2211"/>
                    <Edge fillStyle0="1" fillStyle1="4" edges="
!154 -2222[285 -2183 434 -2056!434 -2056[517 -1984 547 -1840!547 -1840[566 -1748 567 -1589!567 -1589[569 -1471 550 -1374!550 -1374|534 -1261!534 -1261[530 -1241 510 -1210!510 -1210|482 -1161!482 -1161[474 -1140 471 -1106!471 -1106|467
 -1049!467 -1049[458 -934 434 -845!434 -845[391 -699 338 -701!338 -701[316 -701 273 -723!273 -723[231 -742 210 -742!210 -742[193 -823 12 -863!12 -863|9 -863!9 -863|29 -905!29 -905|55 -955!55 -955[72 -990 71 -1009!71 -1009|67 -1026!67
 -1026[49 -1063 46 -1088!46 -1088[43 -1121 63 -1149!63 -1149[81 -1175 123 -1202!123 -1202|192 -1245!192 -1245[197 -1248 192 -1264!192 -1264|182 -1277!182 -1277|126 -1242!126 -1242|72 -1201!72 -1201[53 -1249 120 -1364!120 -1364[130 -1381
 154 -1399!154 -1399|189 -1429!189 -1429[220 -1468 207 -1536!207 -1536[205 -1546 163 -1616!163 -1616[130 -1671 146 -1695!146 -1695[150 -1701 143 -1715!143 -1715[137 -1730 135 -1725!135 -1725[110 -1687 137 -1640!137 -1640|184 -1557!184
 -1557[205 -1508 183 -1468!183 -1468|166 -1451!166 -1451|145 -1439!145 -1439[99 -1400 73 -1327!73 -1327[47 -1250 65 -1193!65 -1193[35 -1162 31 -1122!31 -1122[27 -1083 53 -1025!53 -1025|55 -1025!55 -1025|53 -1016!53 -1016|34 -971!34 -971
|-35 -958!-35 -958|-91 -947!-91 -947|-145 -946!-145 -946[-158 -951 -168 -1017!-168 -1017|-175 -1095!-175 -1095[-192 -1223 -200 -1375!-200 -1375[-208 -1520 -197 -1650!-197 -1650|-187 -1733!-187 -1733[-174 -1788 -147 -1802!-147 -1802|-122
 -1807!-122 -1807|-98 -1809!-98 -1809[-62 -1816 -15 -1838!-15 -1838[60 -1871 117 -1940!117 -1940[165 -1997 173 -2076!173 -2076[179 -2145 154 -2222!187 -677[200 -702 215 -706!215 -706|256 -695!256 -695[299 -677 313 -673!313 -673[357 -659
 370 -673!370 -673|406 -721!406 -721[401 -479 356 -316!356 -316[292 -85 143 17!143 17[135 23 142 46!142 46[150 70 156 66!156 66[282 -4 346 -167!346 -167|365 -222!365 -222|367 -218!367 -218|390 -180!390 -180[425 -114 445 -11!445 -11[454
 40 459 111!459 111[473 270 435 384!435 384[382 546 241 503!241 503[129 451 29 364!29 364[-68 280 -140 175!-140 175[-215 66 -268 -109!-268 -109|-238 -236!-238 -236[-216 -307 -172 -329!-172 -329[-166 -272 -178 -162!-178 -162[-178 -68 -112
 -17!-112 -17|-110 -18!-110 -18[-98 -44 -98 -82!-98 -82|-102 -146!-102 -146[-105 -190 -97 -236!-97 -236[-84 -304 -55 -307!-55 -307[-27 -310 7 -334!7 -334[53 -367 88 -438!88 -438[103 -465 139 -561!139 -561|187 -677"/>
                    <Edge fillStyle0="1" fillStyle1="3" edges="
!122 -577[87 -483 62 -441!62 -441[17 -366 -44 -344!-44 -344|-76 -331!-76 -331|-96 -298!-96 -298[-109 -272 -115 -216!-115 -216|-114 -130!-114 -130[-110 -91 -114 -68!-114 -68[-169 -60 -168 -130!-168 -130|-168 -171!-168 -171|-159 -258!-159
 -258[-155 -310 -163 -346!-163 -346[-169 -366 -173 -365!-173 -365[-221 -347 -244 -274!-244 -274[-257 -233 -271 -155!-271 -155[-283 -116 -302 -86!-302 -86[-330 -46 -346 -142!-346 -142[-346 -170 -334 -212!-334 -212|-302 -307!-302 -307[-280
 -368 -273 -403!-273 -403[-271 -407 -275 -421!-275 -421[-278 -434 -283 -432!-283 -432[-330 -418 -390 -336!-390 -336[-448 -256 -494 -243!-494 -243[-479 -298 -435 -350!-435 -350[-406 -385 -346 -437!-346 -437|-296 -484!-296 -484[-271 -517
 -283 -548!-283 -548[-293 -575 -339 -563!-339 -563[-389 -540 -403 -536!-403 -536|-442 -526!-442 -526[-467 -520 -458 -528!-458 -528|-429 -544!-429 -544|-342 -597!-342 -597|-255 -646!-255 -646|-208 -657!-208 -657|-161 -659!-161 -659[-134
 -662 -93 -706!-93 -706[-46 -753 0 -846!0 -846[175 -804 181 -724!181 -724[163 -700 144 -645!144 -645|122 -577"/>
                    <Edge fillStyle0="1" fillStyle1="2" edges="
!-705 -3132|-762 -3031!-762 -3031[-808 -3080 -769 -3161!-769 -3161[-737 -3146 -705 -3132"/>
                    <Edge fillStyle0="1" fillStyle1="3" edges="
!-695 -3011|-608 -3014!-608 -3014[-597 -3015 -591 -3022!-591 -3022[-585 -3031 -587 -3042!-587 -3042|-590 -3063!-590 -3063[-592 -3078 -605 -3078!-605 -3078|-616 -3074!-616 -3074|-697 -3024!-697 -3024|-705 -3014!-705 -3014|-695 -3011!-220
 -3068[-234 -3048 -230 -3042!-230 -3042|-211 -3032!-211 -3032|-171 -3015!-171 -3015|-127 -2990!-127 -2990[-101 -2975 -95 -2975!-95 -2975|-94 -2975!-94 -2975[-86 -3001 -131 -3051!-131 -3051|-177 -3096!-177 -3096|-188 -3099!-188 -3099[-201
 -3099 -205 -3088!-205 -3088|-220 -3068"/>
                    <Edge fillStyle0="1" fillStyle1="6" edges="
!-153 -2866[-131 -2841 -155 -2798!-155 -2798[-171 -2770 -197 -2763!-197 -2763[-224 -2755 -251 -2769!-251 -2769[-276 -2784 -301 -2819!-301 -2819[-320 -2847 -286 -2877!-286 -2877[-246 -2908 -198 -2895!-198 -2895[-175 -2890 -153 -2866"/>
                    <Edge fillStyle0="1" fillStyle1="3" edges="
!-153 -2902[-221 -2986 -300 -2926!-300 -2926|-301 -2925!-301 -2925|-302 -2925!-302 -2925[-335 -2894 -330 -2848!-330 -2848[-324 -2807 -294 -2770!-294 -2770[-259 -2726 -222 -2714!-222 -2714[-177 -2702 -143 -2745!-143 -2745[-85 -2818 -153
 -2902!-444 -2885[-466 -2833 -487 -2799!-487 -2799[-500 -2778 -536 -2731!-536 -2731|-570 -2689!-570 -2689[-582 -2673 -571 -2655!-571 -2655|-524 -2585!-524 -2585[-514 -2572 -497 -2572!-497 -2572[-484 -2572 -474 -2578!-474 -2578[-465 -2580
 -463 -2586!-463 -2586[-460 -2593 -465 -2600!-465 -2600|-504 -2653!-504 -2653|-511 -2670!-511 -2670|-506 -2688!-506 -2688|-462 -2773!-462 -2773[-437 -2823 -420 -2879!-420 -2879[-414 -2900 -425 -2902!-425 -2902|-426 -2902!-426 -2902[-437
 -2902 -444 -2885!-538 -2933|-538 -2935!-538 -2935|-539 -2935!-539 -2935|-540 -2938!-540 -2938[-563 -2961 -596 -2956!-596 -2956[-626 -2951 -651 -2928!-651 -2928[-676 -2907 -679 -2871!-679 -2871[-683 -2837 -666 -2807!-666 -2807[-632 -2750
 -558 -2813!-558 -2813[-531 -2836 -523 -2867!-523 -2867[-516 -2899 -535 -2928!-535 -2928|-538 -2933"/>
                    <Edge fillStyle0="1" fillStyle1="6" edges="
!-558 -2876|-594 -2845!-594 -2845[-606 -2835 -627 -2830!-627 -2830|-647 -2831!-647 -2831[-661 -2834 -660 -2839!-660 -2839[-654 -2874 -614 -2896!-614 -2896[-574 -2920 -544 -2900!-544 -2900|-545 -2894!-545 -2894|-558 -2876"/>
                    <Edge fillStyle0="1" fillStyle1="7" edges="
!-488 -2455[-439 -2463 -390 -2457!-390 -2457|-390 -2387!-390 -2387|-488 -2399!-488 -2399|-488 -2455"/>
                    <Edge fillStyle0="1" fillStyle1="3" edges="
!-532 -2270|-496 -2251!-496 -2251|-467 -2246!-467 -2246|-431 -2252!-431 -2252[-423 -2254 -417 -2261!-417 -2261[-411 -2270 -413 -2277!-413 -2277[-417 -2294 -435 -2294!-435 -2294|-440 -2293!-440 -2293|-529 -2282!-529 -2282|-539 -2277!-539
 -2277|-532 -2270!-671 -2353[-550 -2375 -427 -2354!-427 -2354[-301 -2333 -198 -2271!-198 -2271[-188 -2264 -178 -2276!-178 -2276[-169 -2285 -169 -2296!-169 -2296[-170 -2479 -381 -2494!-381 -2494[-468 -2500 -552 -2469!-552 -2469[-639 -2436
 -683 -2377!-683 -2377[-691 -2365 -684 -2359!-684 -2359[-682 -2350 -671 -2353"/>
                    <Edge fillStyle0="1" fillStyle1="8" edges="
!-593 -2151|-557 -2129!-557 -2129[-577 -2069 -552 -2004!-552 -2004|-505 -1904!-505 -1904[-472 -1840 -486 -1753!-486 -1753[-499 -1672 -531 -1512!-531 -1512[-538 -1561 -555 -1591!-555 -1591|-567 -1608!-567 -1608|-569 -1625!-569 -1625|-551
 -1673!-551 -1673[-535 -1712 -540 -1738!-540 -1738[-545 -1770 -565 -1772!-565 -1772[-576 -1773 -608 -1758!-608 -1758[-636 -1741 -650 -1737!-650 -1737[-675 -1728 -694 -1744!-694 -1744|-759 -1793!-759 -1793[-682 -1920 -592 -2132!-592 -2132
[-589 -2137 -593 -2151"/>
                    <Edge fillStyle0="1" fillStyle1="7" edges="
!-369 -2382|-369 -2454!-369 -2454[-331 -2447 -296 -2429!-296 -2429|-296 -2362!-296 -2362|-369 -2382!-275 -2353|-275 -2416!-275 -2416[-225 -2382 -211 -2325!-211 -2325|-275 -2353"/>
                    <Edge fillStyle0="1" fillStyle1="4" edges="
!-615 -2162[-713 -1934 -794 -1810!-794 -1810[-798 -1802 -794 -1785!-794 -1785|-781 -1763!-781 -1763|-722 -1724!-722 -1724|-691 -1697!-691 -1697[-672 -1680 -657 -1682!-657 -1682|-625 -1694!-625 -1694|-594 -1709!-594 -1709|-567 -1721!-567
 -1721|-586 -1672!-586 -1672[-596 -1644 -592 -1622!-592 -1622[-589 -1606 -568 -1573!-568 -1573[-551 -1547 -547 -1491!-547 -1491|-545 -1403!-545 -1403|-542 -1364!-542 -1364|-537 -1292!-537 -1292|-534 -1279!-534 -1279|-517 -1140!-517 -1140
[-508 -1061 -507 -1001!-507 -1001[-507 -949 -596 -988!-596 -988[-670 -1021 -719 -1066!-719 -1066[-722 -1138 -732 -1189!-732 -1189[-744 -1261 -775 -1385!-775 -1385|-822 -1582!-822 -1582[-825 -1599 -835 -1607!-835 -1607[-845 -1615 -841
 -1591!-841 -1591|-808 -1451!-808 -1451[-887 -1565 -892 -1720!-892 -1720[-898 -1880 -819 -1989!-819 -1989[-746 -2091 -615 -2162!-306 -533|-296 -534!-296 -534|-296 -532!-296 -532[-307 -508 -347 -476!-347 -476|-351 -519!-351 -519|-306 -533
!-368 -513|-362 -463!-362 -463|-367 -460!-367 -460[-430 -405 -462 -361!-462 -361[-505 -302 -514 -236!-514 -236[-514 -206 -502 -207!-502 -207[-456 -212 -413 -260!-413 -260[-390 -287 -346 -349!-346 -349|-332 -279!-332 -279[-355 -206 -355
 -157!-355 -157[-356 -91 -321 -34!-321 -34|-317 -31!-317 -31[-295 -48 -279 -81!-279 -81[-232 56 -179 150!-179 150[-126 246 -53 326!-53 326|-53 329!-53 329|-53 337!-53 337[-55 414 -68 519!-68 519|-73 549!-73 549|-75 566!-75 566|-77 576
!-77 576|-81 598!-81 598|-85 614!-85 614|-92 655!-92 655[-171 750 -279 784!-279 784[-396 821 -501 767!-501 767|-549 598!-549 598|-561 549!-561 549[-602 396 -637 221!-637 221[-699 -79 -719 -294!-719 -294[-745 -580 -712 -813!-712 -813[-657
 -769 -581 -729!-581 -729[-463 -667 -324 -647!-324 -647[-388 -604 -421 -586!-421 -586|-460 -565!-460 -565[-479 -550 -478 -529!-478 -529[-476 -491 -437 -494!-437 -494[-419 -495 -373 -511!-373 -511|-368 -513!-329 -366[-315 -382 -295 -391
!-295 -391|-319 -316!-319 -316|-329 -366"/>
                    <Edge fillStyle0="1" fillStyle1="9" edges="
!-497 814[-391 871 -270 835!-270 835[-161 802 -80 706!-80 706|-55 758!-55 758[-42 787 -41 815!-41 815[-41 849 -69 872!-69 872[-90 888 -129 903!-129 903|-172 905!-172 905|-185 897!-185 897[-191 891 -190 895!-190 895[-198 869 -206 876!-206
 876|-304 977!-304 977[-360 1027 -424 1051!-424 1051[-640 1135 -752 1078!-752 1078[-795 1055 -665 943!-665 943[-571 861 -497 814!567 207[585 221 598 248!598 248[613 281 590 288!590 288[577 291 569 299!569 299[561 309 563 330!563 330[565
 347 573 361!573 361|601 417!601 417[608 429 592 514!592 514|592 520!592 520|586 549!586 549|574 598!574 598[557 654 527 702!527 702[472 790 383 835!383 835[294 881 257 848!257 848[238 830 234 787!234 787|234 721!234 721[235 664 246 598
!246 598|253 552!253 552|362 549!362 549[420 523 451 434!451 434[490 323 481 152!481 152[493 163 524 180!524 180[555 197 567 207"/>
                  </edges>
                </DOMShape>
              </elements>
            </DOMFrame>
          </frames>
        </DOMLayer>
      </layers>
    </DOMTimeline>
  </timeline>
</DOMSymbolItem>