<DOMSymbolItem xmlns:xsi="http://www.w3.org/2001/XMLSchema-instance" xmlns="http://ns.adobe.com/xfl/2008/" name="Shapes/Shape 631" itemID="591c88da-00000215" symbolType="graphic" lastModified="1495042266">
  <timeline>
    <DOMTimeline name="Shape 631">
      <layers>
        <DOMLayer name="Shape Sublayer 1" color="#4F80FF" current="true" isSelected="true">
          <frames>
            <DOMFrame index="0" keyMode="8704">
              <elements>
                <DOMShape isFloating="true">
                  <fills>
                    <FillStyle index="1">
                      <SolidColor color="#0067B1"/>
                    </FillStyle>
                    <FillStyle index="2">
                      <SolidColor/>
                    </FillStyle>
                  </fills>
                  <edges>
                    <Edge fillStyle0="2" edges="!328 -324[268 -352 227 -352!227 -352[198 -352 171 -340!171 -340[134 -319 88 -269!88 -269|60 -239!60 -239|41 -218!41 -218[-42 -129 -87 -89!-87 -89|-147 -102!-147 -102[-261 -127 -332 -132!-332 -132|-368 -134!-368 -134[-456 -134 -478 -107
!-478 -107[-486 -98 -484 -86!-484 -86[-481 -69 -463 -69!-463 -69[-453 -70 -448 -79!-448 -79|-390 -85!-390 -85|-339 -81!-339 -81[-266 -71 -162 -41!-162 -41|-149 -37!-149 -37[-229 24 -336 24!-336 24|-380 21!-380 21|-382 20!-382 20|-467
 19!-467 19|-658 29!-658 29[-833 53 -919 98!-919 98[-978 130 -1010 186!-1010 186[-1026 214 -1031 243!-1031 243|-1032 260!-1032 260|-1042 265!-1042 265[-1057 274 -1060 287!-1060 287|-1060 291!-1060 291[-1060 307 -1044 311!-1044 311|-1040
 311!-1040 311[-1027 311 -1022 300!-1022 300|-1012 295!-1012 295|-1009 293!-1009 293|-1007 293!-1007 293|-1006 292!-1006 292|-1005 292!-1005 292|-991 279!-991 279|-990 268!-990 268|-990 266!-990 266|-988 251!-988 251[-985 231 -971 209
!-971 209[-942 166 -895 144!-895 144[-819 109 -652 92!-652 92|-555 89!-555 89|-385 95!-385 95|-355 97!-355 97|-301 100!-301 100|-228 91!-228 91[-159 73 -83 21!-83 21|-47 -6!-47 -6|27 19!27 19|198 75!198 75[261 98 333 98!333 98[414 98
 489 71!489 71[564 43 614 -5!614 -5|689 -66!689 -66[699 -75 753 -93!753 -93|794 -106!794 -106[878 -131 921 -152!921 -152|936 -151!936 -151[978 -151 1010 -173!1010 -173[1019 -177 1019 -189!1019 -189[1019 -200 1011 -206!1011 -206[924 -271
 873 -378!873 -378[869 -387 859 -390!859 -390[849 -391 841 -384!841 -384|824 -364!824 -364|738 -370!738 -370[612 -370 541 -316!541 -316|539 -315!539 -315[504 -280 456 -282!456 -282[408 -283 336 -321!336 -321|328 -324"/>
                    <Edge fillStyle0="1" fillStyle1="2" edges="
!259 -331|181 -325!181 -325[151 -309 122 -278!122 -278|75 -228!75 -228[-36 -109 -81 -69!-81 -69|-151 -85!-151 -85|-334 -114!-334 -114|-421 -112!-421 -112[-466 -104 -464 -92!-464 -92[-465 -102 -421 -106!-421 -106|-336 -103!-336 -103[-263
 -93 -157 -63!-157 -63|-106 -48!-106 -48|-122 -36!-122 -36[-173 9 -244 29!-244 29|-383 38!-383 38|-655 47!-655 47[-828 71 -909 113!-909 113[-963 142 -993 193!-993 193[-1006 217 -1011 243!-1011 243|-1012 265!-1012 265|-1011 269!-1011 269
|-1012 271!-1012 271|-1009 269!-1009 269|-1010 265!-1010 265|-1008 244!-1008 244[-1002 219 -988 196!-988 196[-958 149 -904 123!-904 123[-819 84 -653 70!-653 70[-552 62 -384 73!-384 73|-314 77!-314 77|-233 69!-233 69[-166 51 -94 2!-94
 2|-51 -31!-51 -31|205 54!205 54[301 88 413 68!413 68[529 46 602 -23!602 -23|676 -84!676 -84[690 -96 747 -115!747 -115|830 -140!830 -140[881 -156 918 -175!918 -175|936 -173!936 -173[971 -173 999 -192!999 -192[908 -260 855 -372!855 -372
|834 -344!834 -344|732 -352!732 -352[617 -351 553 -303!553 -303[476 -227 328 -305!328 -305|259 -331"/>
                    <Edge fillStyle0="2" edges="
!108 -148|151 -191!151 -191|196 -233!196 -233[213 -246 228 -246!228 -246[249 -246 286 -223!286 -223[317 -201 362 -185!362 -185[416 -167 470 -167!470 -167[562 -167 617 -222!617 -222[632 -237 678 -237!678 -237|716 -236!716 -236|785 -235
!785 -235|716 -209!716 -209[671 -196 624 -160!624 -160[595 -139 552 -97!552 -97|544 -90!544 -90[484 -28 398 -7!398 -7[312 15 221 -9!221 -9|52 -52!52 -52|19 -61!19 -61|108 -148"/>
                    <Edge fillStyle0="1" fillStyle1="2" edges="
!205 -264[238 -278 298 -242!298 -242[358 -198 444 -190!444 -190[545 -181 603 -238!603 -238[624 -260 691 -259!691 -259[794 -257 824 -261!824 -261|833 -235!833 -235|721 -192!721 -192[678 -180 629 -142!629 -142|558 -78!558 -78[493 -11 402
 11!402 11[313 33 217 8!217 8|-23 -54!-23 -54|117 -187!117 -187|205 -264"/>
                  </edges>
                </DOMShape>
              </elements>
            </DOMFrame>
          </frames>
        </DOMLayer>
      </layers>
    </DOMTimeline>
  </timeline>
</DOMSymbolItem>