<DOMSymbolItem xmlns:xsi="http://www.w3.org/2001/XMLSchema-instance" xmlns="http://ns.adobe.com/xfl/2008/" name="Shapes_o/Shape 1620" itemID="591c88da-000005b3" symbolType="graphic" lastModified="1495042266">
  <timeline>
    <DOMTimeline name="Shape 1620">
      <layers>
        <DOMLayer name="Shape Sublayer 1" color="#4F80FF" current="true" isSelected="true">
          <frames>
            <DOMFrame index="0" keyMode="8704">
              <elements>
                <DOMShape isFloating="true">
                  <fills>
                    <FillStyle index="1">
                      <SolidColor/>
                    </FillStyle>
                    <FillStyle index="2">
                      <SolidColor color="#D4D4D4"/>
                    </FillStyle>
                    <FillStyle index="3">
                      <SolidColor color="#666666"/>
                    </FillStyle>
                    <FillStyle index="4">
                      <SolidColor color="#B2B2B2"/>
                    </FillStyle>
                  </fills>
                  <edges>
                    <Edge fillStyle0="1" fillStyle1="3" edges="!3731 1933|3772 1939!3772 1939|3810 1935!3810 1935|3819 1931!3819 1931|3810 2184!3810 2184|3801 2187!3801 2187|3763 2195!3763 2195|3726 2188!3726 2188|3714 2180!3714 2180|3708 2172!3708 2172|3714 1925!3714 1925|3731 1933"/>
                    <Edge fillStyle0="1" fillStyle1="2" edges="!3719 1919|3715 1912!3715 1912[3716 1906 3727 1900!3727 1900|3766 1899!3766 1899|3807 1905!3807 1905|3816 1914!3816 1914|3821 1918!3821 1918|3809 1931!3809 1931|3771 1934!3771 1934|3732 1928!3732 1928|3719 1919"/>
                    <Edge fillStyle0="1" edges="!3707 1914|3698 2257!3698 2257|3707 2272!3707 2272|3727 2283!3727 2283|3752 2286!3752 2286|3776 2286!3776 2286|3795 2280!3795 2280|3814 2264!3814 2264|3830 1918!3830 1918[3831 1913 3825 1907!3825 1907|3809 1896!3809 1896[3792 1888 3766
 1887!3766 1887|3725 1893!3725 1893[3707 1898 3707 1914"/>
                    <Edge fillStyle0="1" fillStyle1="4" edges="
!3725 2190|3762 2196!3762 2196|3804 2191!3804 2191|3810 2188!3810 2188|3807 2251!3807 2251|3804 2260!3804 2260[3792 2268 3769 2269!3769 2269|3729 2264!3729 2264[3713 2259 3708 2247!3708 2247|3707 2180!3707 2180|3725 2190"/>
                    <Edge fillStyle0="1" fillStyle1="2" edges="
!3809 2261|3800 2268!3800 2268[3791 2277 3769 2278!3769 2278|3731 2275!3731 2275|3714 2266!3714 2266[3708 2262 3708 2255!3708 2255|3708 2253!3708 2253|3727 2269!3727 2269|3771 2272!3771 2272[3792 2269 3802 2262!3802 2262|3809 2258!3809
 2258|3809 2261"/>
                  </edges>
                </DOMShape>
              </elements>
            </DOMFrame>
          </frames>
        </DOMLayer>
      </layers>
    </DOMTimeline>
  </timeline>
</DOMSymbolItem>