<DOMSymbolItem xmlns:xsi="http://www.w3.org/2001/XMLSchema-instance" xmlns="http://ns.adobe.com/xfl/2008/" name="Shapes_o/Shape 405" itemID="591c88da-000002e6" symbolType="graphic" lastModified="1495042266">
  <timeline>
    <DOMTimeline name="Shape 405">
      <layers>
        <DOMLayer name="Shape Sublayer 1" color="#4F80FF" current="true" isSelected="true">
          <frames>
            <DOMFrame index="0" keyMode="8704">
              <elements>
                <DOMShape isFloating="true">
                  <fills>
                    <FillStyle index="1">
                      <SolidColor color="#B2B2B2"/>
                    </FillStyle>
                    <FillStyle index="2">
                      <SolidColor/>
                    </FillStyle>
                    <FillStyle index="3">
                      <SolidColor color="#D4D4D4"/>
                    </FillStyle>
                    <FillStyle index="4">
                      <SolidColor color="#666666"/>
                    </FillStyle>
                  </fills>
                  <edges>
                    <Edge fillStyle0="1" fillStyle1="2" edges="!24 -1092[-63 -1029 -94 -886!-94 -886[-103 -846 -99 -771!-99 -771[-106 -716 -172 -717!-172 -717|-172 -670!-172 -670|-162 -617!-162 -617[-150 -555 -154 -533!-154 -533|-158 -492!-158 -492[-67 -508 79 -559!79 -559|206 -607!206 -607[252 -581
 284 -530!284 -530|306 -484!306 -484|244 -434!244 -434[174 -382 135 -375!135 -375[104 -368 -34 -407!-34 -407[-157 -441 -155 -426!-155 -426|-145 -354!-145 -354|-144 -351!-144 -351[-96 -351 -50 -312!-50 -312|-24 -280!-24 -280[-16 -269 10
 -264!10 -264[51 -256 97 -189!97 -189[89 -254 113 -306!113 -306[124 -330 159 -348!159 -348|218 -373!218 -373|312 -418!312 -418[366 -448 393 -482!393 -482[409 -503 349 -588!349 -588|272 -688!272 -688|201 -781!201 -781[178 -808 84 -750
!84 -750|66 -746!66 -746[54 -746 51 -754!51 -754[23 -824 33 -889!33 -889[45 -961 100 -1005!100 -1005[182 -1070 366 -1066!366 -1066[335 -1084 303 -1113!303 -1113|245 -1169!245 -1169[218 -1195 133 -1156!133 -1156[82 -1132 24 -1092"/>
                    <Edge fillStyle0="3" fillStyle1="2" edges="
!397 -1045[232 -1056 131 -993!131 -993[82 -962 70 -896!70 -896[60 -840 80 -777!80 -777[165 -827 216 -804!216 -804|252 -770!252 -770|281 -728!281 -728|377 -591!377 -591[424 -522 427 -502!427 -502[431 -466 371 -426!371 -426[353 -414 252
 -370!252 -370[174 -336 148 -299!148 -299[127 -269 130 -214!130 -214[132 -172 147 -128!147 -128|147 -124!147 -124|184 -127!184 -127|219 -131!219 -131[279 -130 353 -83!353 -83[383 -66 409 -14!409 -14[429 24 438 64!438 64[448 108 444 147
!444 147[470 111 508 39!508 39|568 -70!568 -70[592 -108 623 -131!623 -131[648 -151 691 -169!691 -169[690 -269 714 -354!714 -354[742 -458 800 -505!800 -505|778 -556!778 -556|773 -556!773 -556|771 -550!771 -550|771 -549!771 -549|770 -548
!770 -548|749 -516!749 -516[721 -488 683 -499!683 -499[639 -509 592 -555!592 -555[545 -602 511 -671!511 -671[480 -732 468 -797!468 -797[456 -861 470 -899!470 -899[485 -938 500 -947!500 -947|503 -948!503 -948|501 -951!501 -951|506 -964
!506 -964[454 -1014 401 -1045!401 -1045|397 -1045"/>
                    <Edge fillStyle1="2" edges="
!344 -1108[364 -1086 404 -1063!404 -1063|412 -1058!412 -1058|508 -998!508 -998|521 -985!521 -985|522 -986!522 -986|524 -983!524 -983|544 -964!544 -964|550 -958!550 -958|561 -956!561 -956|563 -956!563 -956|563 -957!563 -957|565 -955!565
 -955|610 -934!610 -934|611 -933!611 -933|612 -934!612 -934[652 -940 694 -916!694 -916[737 -892 767 -847!767 -847[817 -773 819 -688!819 -688[821 -642 794 -602!794 -602|832 -526!832 -526|859 -537!859 -537|871 -535!871 -535|907 -496!907
 -496[1001 -554 1097 -552!1097 -552[1211 -549 1240 -449!1240 -449[1247 -425 1240 -397!1240 -397[1236 -382 1264 -358!1264 -358[1377 -262 1471 -194!1471 -194|1550 -150!1550 -150[1605 -119 1614 -94!1614 -94|1619 -37!1619 -37[1621 7 1628
 11!1628 11[1669 34 1711 77!1711 77[1798 166 1701 378!1701 378|1704 382!1704 382[1749 501 1756 606!1756 606[1764 740 1709 829!1709 829|1702 833!1702 833[1706 925 1729 982!1729 982|1729 992!1729 992[1631 1113 1569 1175!1569 1175[1546 1198
 1511 1208!1511 1208|1444 1220!1444 1220|1161 1259!1161 1259|1170 1261!1170 1261|1234 1251!1234 1251|1429 1948!1429 1948|1441 1986!1441 1986|1471 1998!1471 1998[1511 2014 1544 2083!1544 2083|1590 2197!1590 2197|1606 2201!1606 2201|1615
 2210!1615 2210|1620 2237!1620 2237|1690 2694!1690 2694[1689 2685 1698 2690!1698 2690|1725 2703!1725 2703|1764 2715!1764 2715[1792 2724 1799 2735!1799 2735[1819 2764 1829 2835!1829 2835|1845 2942!1845 2942|1841 2949!1841 2949|1626 3060
!1626 3060[1504 3120 1403 3147!1403 3147|772 3316!772 3316|752 3313!752 3313[740 3308 741 3300!741 3300|781 2992!781 2992[788 2936 843 2878!843 2878[898 2821 955 2808!955 2808|964 2806!964 2806[1037 2807 1194 2840!1194 2840[1153 2784
 1054 2667!1054 2667[961 2556 916 2493!916 2493[908 2483 900 2441!900 2441[857 2348 754 2226!754 2226|584 2025!584 2025|584 2023!584 2023|583 2022!583 2022|582 2020!582 2020|582 2019!582 2019[579 2014 584 2011!584 2011|586 2008!586 2008
|652 1947!652 1947|648 1941!648 1941[606 1972 553 1983!553 1983[421 2013 333 1871!333 1871|317 1844!317 1844|311 1864!311 1864|297 1912!297 1912|290 1948!290 1948|535 2245!535 2245|584 2237!584 2237|620 2229!620 2229|656 2233!656 2233
[689 2254 733 2306!733 2306|802 2388!802 2388|805 2399!805 2399|267 3259!267 3259|250 3263!250 3263[239 3261 234 3255!234 3255|7 3044!7 3044[-36 3004 -52 2924!-52 2924[-68 2844 -44 2791!-44 2791|-42 2789!-42 2789[-20 2762 19 2734!19 2734
|90 2690!90 2690|175 2640!175 2640|198 2628!198 2628|195 2625!195 2625|84 2576!84 2576[67 2582 71 2570!71 2570|-90 2499!-90 2499[-116 2488 -181 2464!-181 2464[-239 2441 -262 2414!-262 2414|-468 2169!-468 2169|-469 2162!-469 2162|-462
 2158!-462 2158|-306 2129!-306 2129|-249 2115!-249 2115|-430 1959!-430 1959[-439 1950 -436 1945!-436 1945[-411 1883 -406 1792!-406 1792|-404 1633!-404 1633|-395 1398!-395 1398[-388 1264 -374 1165!-374 1165[-372 1151 -352 1157!-352 1157
|-351 1157!-351 1157[-223 1194 -151 1283!-151 1283[-159 1174 -157 1066!-157 1066|-267 964!-267 964|-314 1009!-314 1009|-336 1010!-336 1010[-353 1006 -351 997!-351 997|-350 992!-350 992|-400 1077!-400 1077|-443 1152!-443 1152[-472 1197
 -503 1213!-503 1213|-546 1232!-546 1232[-529 1240 -534 1242!-534 1242[-531 1246 -542 1244!-542 1244|-564 1239!-564 1239[-664 1276 -781 1292!-781 1292|-740 1294!-740 1294|-730 1297!-730 1297[-721 1299 -716 1304!-716 1304[-710 1310 -714
 1314!-714 1314|-721 1319!-721 1319|-785 1355!-785 1355[-820 1372 -854 1370!-854 1370|-1151 1350!-1151 1350|-1210 1349!-1210 1349[-1250 1346 -1259 1326!-1259 1326|-1262 1316!-1262 1316[-1303 1350 -1350 1362!-1350 1362|-1447 1359!-1447
 1359[-1522 1394 -1589 1368!-1589 1368[-1661 1342 -1677 1262!-1677 1262|-1691 1259!-1691 1259[-1736 1244 -1750 1212!-1750 1212[-1766 1176 -1754 1132!-1754 1132|-1737 1095!-1737 1095[-1774 1064 -1758 1006!-1758 1006[-1748 972 -1723 948
!-1723 948[-1664 892 -1521 879!-1521 879|-1519 884!-1519 884[-1477 829 -1415 826!-1415 826|-1400 826!-1400 826|-1396 827!-1396 827|-1366 832!-1366 832|-1327 849!-1327 849|-1326 849!-1326 849|-1307 862!-1307 862|-998 702!-998 702|-995
 701!-995 701[-1065 625 -1054 543!-1054 543[-1050 515 -1023 458!-1023 458[-1008 428 -1010 417!-1010 417|-1030 373!-1030 373[-1049 329 -1035 300!-1035 300|-991 229!-991 229[-965 175 -956 144!-956 144[-939 86 -961 62!-961 62[-991 28 -984
 -21!-984 -21[-978 -66 -946 -101!-946 -101[-897 -153 -834 -177!-834 -177[-770 -202 -700 -197!-700 -197|-698 -203!-698 -203[-711 -199 -707 -211!-707 -211[-687 -283 -634 -322!-634 -322[-585 -359 -519 -361!-519 -361|-521 -356!-521 -356|-500
 -394!-500 -394[-485 -429 -484 -495!-484 -495|-483 -598!-483 -598[-474 -748 -461 -846!-461 -846|-449 -921!-449 -921[-439 -964 -418 -990!-418 -990[-360 -1066 -278 -1110!-278 -1110[-182 -1162 -102 -1136!-102 -1136[-15 -1157 84 -1157!84
 -1157[191 -1208 261 -1187!261 -1187[279 -1181 306 -1152!306 -1152|344 -1108"/>
                    <Edge fillStyle0="3" fillStyle1="2" edges="
!636 -888[604 -872 602 -824!602 -824[599 -775 627 -721!627 -721[665 -646 720 -628!720 -628|766 -630!766 -630[783 -638 792 -658!792 -658[805 -705 786 -764!786 -764[770 -815 741 -847!741 -847[715 -877 686 -888!686 -888[658 -899 636 -888"/>
                    <Edge fillStyle0="3" fillStyle1="4" edges="
!671 -827[694 -838 723 -806!723 -806[738 -788 747 -762!747 -762[757 -731 750 -707!750 -707|738 -693!738 -693[729 -688 716 -693!716 -693[687 -701 668 -742!668 -742[654 -770 654 -795!654 -795[655 -819 671 -827"/>
                    <Edge fillStyle0="1" fillStyle1="2" edges="
!549 -924[509 -899 500 -858!500 -858[483 -784 559 -654!559 -654|564 -657!564 -657[536 -708 530 -764!530 -764[523 -815 535 -851!535 -851[546 -885 567 -894!567 -894[591 -906 591 -918!591 -918|585 -928!585 -928|551 -925!551 -925|549 -924
!573 -631[649 -500 733 -536!733 -536|734 -536!734 -536|734 -537!734 -537[746 -560 739 -564!739 -564|729 -563!729 -563|679 -559!679 -559[615 -573 578 -634!578 -634|573 -631"/>
                    <Edge fillStyle0="3" fillStyle1="2" edges="
!47 -65|46 -70!46 -70[44 -82 62 -82!62 -82[80 -83 82 -73!82 -73|83 -68!83 -68[85 -57 67 -56!67 -56[49 -55 47 -65!106 -81[92 -89 76 -117!76 -117|52 -159!52 -159[5 -225 -55 -223!-55 -223|-59 -228!-59 -228[-80 -294 -170 -305!-170 -305|-189
 -295!-189 -295[-213 -287 -222 -153!-222 -153|-223 -138!-223 -138|-227 -125!-227 -125[-174 -118 -127 -70!-127 -70[-84 -27 -63 30!-63 30[-44 79 -51 136!-51 136|43 151!43 151|97 159!97 159[121 155 124 120!124 120[127 91 123 67!123 67[117
 30 96 27!96 27|50 33!50 33|5 45!5 45[-7 48 -18 39!-18 39[-29 31 -12 27!-12 27|47 12!47 12|108 8!108 8[135 14 147 37!147 37[156 54 160 87!160 87[164 127 155 148!155 148[144 176 109 181!109 181|27 172!27 172|-55 156!-55 156[-65 201 -92
 239!-92 239[-119 277 -158 300!-158 300[-223 337 -291 303!-291 303[-229 407 -144 433!-144 433[-91 450 -32 409!-32 409[42 356 69 352!69 352[107 346 150 314!150 314|223 262!223 262[236 255 255 255!255 255|290 259!290 259[249 214 230 133
!230 133[208 -3 274 -64!274 -64|210 -84!210 -84|156 -79!156 -79|106 -81!272 -2[262 48 270 97!270 97[291 185 339 228!339 228[383 267 396 198!396 198[406 148 398 99!398 99[385 17 329 -31!329 -31[285 -71 272 -2"/>
                    <Edge fillStyle0="1" fillStyle1="2" edges="
!692 -147[648 -124 625 -96!625 -96[594 -58 538 53!538 53[487 153 444 195!444 195|434 198!434 198[416 248 376 275!376 275[362 284 345 286!345 286|335 295!335 295|261 300!261 300[212 297 192 317!192 317[139 368 61 391!61 391|22 398!22 398
|-34 447!-34 447|-44 454!-44 454|-41 455!-41 455[-25 469 -41 485!-41 485|-73 487!-73 487[-96 469 -100 481!-100 481|-96 516!-96 516|-71 604!-71 604|-39 695!-39 695[-12 749 30 750!30 750[52 751 52 773!52 773[52 796 30 795!30 795[-40 793
 -82 709!-82 709[-99 677 -131 563!-131 563[-147 499 -147 480!-147 480[-194 476 -237 447!-237 447[-243 522 -294 577!-294 577[-344 632 -416 647!-416 647|-415 661!-415 661[-413 725 -362 790!-362 790|-276 902!-276 902[-260 930 -222 965!-222
 965|-159 1021!-159 1021|-137 1042!-137 1042|-123 1036!-123 1036[138 916 476 914!476 914|523 914!523 914|548 907!548 907|551 908!551 908|553 907!553 907|632 907!632 907[683 907 712 919!712 919|717 919!717 919[757 894 789 895!789 895|779
 830!779 830|784 822!784 822|1134 574!1134 574|1148 568!1148 568|1147 532!1147 532[1056 583 970 548!970 548[880 512 844 401!844 401|762 152!762 152[717 7 696 -101!696 -101|692 -147"/>
                    <Edge fillStyle0="3" fillStyle1="2" edges="
!747 -130[763 -46 797 66!797 66|859 259!859 259|874 305!874 305[914 188 1054 188!1054 188[1197 188 1243 322!1243 322[1253 350 1251 379!1251 379[1305 372 1364 317!1364 317|1451 220!1451 220[1520 135 1573 36!1573 36[1574 -22 1569 -40!1569
 -40[1560 -73 1523 -93!1523 -93|1453 -136!1453 -136|1386 -185!1386 -185[1277 -268 1182 -351!1182 -351[1179 -354 1181 -358!1181 -358[1202 -403 1179 -442!1179 -442[1159 -475 1112 -500!1112 -500[1065 -524 1001 -509!1001 -509[945 -496 898
 -461!898 -461[874 -444 866 -453!866 -453|844 -480!844 -480[828 -497 819 -488!819 -488[801 -469 787 -434!787 -434|769 -373!769 -373[731 -245 747 -130!1164 -429[1171 -399 1145 -369!1145 -369[1123 -343 1092 -333!1092 -333|1086 -331!1086
 -331[1055 -324 1031 -337!1031 -337[1007 -351 1000 -381!1000 -381[993 -411 1019 -441!1019 -441[1041 -467 1073 -478!1073 -478|1130 -475!1130 -475[1157 -461 1164 -429"/>
                    <Edge fillStyle1="2" edges="
!1056 -396[1063 -381 1077 -373!1077 -373|1108 -369!1108 -369|1113 -381!1113 -381[1118 -394 1109 -415!1109 -415[1095 -443 1061 -443!1061 -443[1050 -442 1050 -424!1050 -424[1050 -408 1056 -396"/>
                    <Edge fillStyle0="4" fillStyle1="2" edges="
!-141 -1123|-200 -1120!-200 -1120[-226 -1111 -257 -1092!-257 -1092|-329 -1039!-329 -1039[-387 -991 -403 -949!-403 -949[-420 -904 -428 -837!-428 -837|-437 -723!-437 -723|-451 -524!-451 -524[-356 -491 -233 -487!-233 -487|-230 -510!-230
 -510[-227 -532 -239 -592!-239 -592|-249 -662!-249 -662|-247 -723!-247 -723|-260 -726!-260 -726[-301 -755 -308 -825!-308 -825[-314 -881 -298 -940!-298 -940[-282 -1000 -241 -1050!-241 -1050[-196 -1104 -141 -1123"/>
                    <Edge fillStyle1="2" edges="
!-857 -31[-853 -3 -818 9!-818 9[-788 18 -795 -24!-795 -24[-804 -55 -835 -64!-835 -64[-864 -72 -857 -31"/>
                    <Edge fillStyle0="1" fillStyle1="2" edges="
!-891 -62[-869 -88 -837 -99!-837 -99|-781 -98!-781 -98[-755 -86 -746 -56!-746 -56|-745 -53!-745 -53|-745 -50!-745 -50[-738 16 -813 43!-813 43[-889 70 -908 -2!-908 -2[-916 -32 -891 -62!-925 -70[-953 -2 -895 44!-895 44|-894 47!-894 47[-909
 131 -942 209!-942 209[-964 256 -985 281!-985 281[-1000 298 -984 338!-984 338|-954 395!-954 395[-913 456 -824 506!-824 506[-779 530 -717 545!-717 545|-601 555!-601 555[-622 524 -632 488!-632 488[-651 412 -597 343!-597 343[-544 275 -465
 272!-465 272[-404 270 -354 296!-354 296|-382 227!-382 227|-381 217!-381 217|-408 163!-408 163|-417 112!-417 112|-452 61!-452 61|-436 86!-436 86|-436 92!-436 92|-560 -65!-560 -65[-627 -158 -643 -243!-643 -243|-661 -183!-661 -183[-664
 -172 -680 -162!-680 -162[-695 -151 -707 -153!-707 -153|-826 -150!-826 -150[-899 -136 -925 -70"/>
                    <Edge fillStyle0="3" fillStyle1="2" edges="
!-192 -772|-213 -758!-213 -758[-226 -746 -227 -738!-227 -738|-227 -731!-227 -731[-222 -728 -228 -726!-228 -726|-231 -662!-231 -662|-219 -583!-219 -583[-208 -531 -212 -507!-212 -507[-224 -436 -206 -336!-206 -336[-184 -347 -162 -350!-162
 -350|-162 -351!-162 -351|-170 -393!-170 -393[-183 -480 -171 -537!-171 -537[-168 -556 -178 -602!-178 -602|-190 -669!-190 -669|-190 -717!-190 -717|-186 -766!-186 -766[-186 -773 -192 -772!-175 -785[-167 -777 -168 -764!-168 -764|-171 -731
!-171 -731[-145 -732 -132 -823!-132 -823|-117 -940!-117 -940[-91 -1033 -26 -1086!-26 -1086[11 -1116 49 -1137!49 -1137|-91 -1119!-91 -1119[-213 -1076 -261 -938!-261 -938[-277 -896 -274 -841!-274 -841[-271 -780 -244 -747!-244 -747|-223
 -774!-223 -774[-208 -788 -196 -790!-196 -790[-183 -793 -175 -785"/>
                    <Edge fillStyle0="4" fillStyle1="2" edges="
!-548 -322|-598 -309!-598 -309|-587 -249!-587 -249[-581 -281 -548 -322!-527 -303[-578 -246 -529 -129!-529 -129[-499 -55 -417 60!-417 60[-409 -10 -369 -59!-369 -59|-372 -66!-372 -66[-369 -110 -347 -163!-347 -163|-350 -170!-350 -170[-345
 -198 -354 -223!-354 -223[-364 -250 -386 -265!-386 -265[-401 -275 -433 -285!-433 -285|-482 -303!-482 -303|-513 -320!-513 -320|-527 -303!-433 -306|-389 -291!-389 -291[-363 -283 -349 -271!-349 -271[-327 -252 -318 -223!-318 -223[-293 -265
 -257 -300!-257 -300|-226 -342!-226 -342|-229 -380!-229 -380[-229 -404 -234 -416!-234 -416[-239 -428 -306 -384!-306 -384[-382 -335 -399 -334!-399 -334[-422 -332 -448 -362!-448 -362|-469 -392!-469 -392[-479 -366 -498 -339!-498 -339|-433
 -306"/>
                    <Edge fillStyle0="3" fillStyle1="2" edges="
!-244 -287[-272 -234 -281 -121!-281 -121|-248 -126!-248 -126[-241 -135 -241 -139!-241 -139|-233 -223!-233 -223[-224 -286 -206 -305!-206 -305[-226 -301 -244 -287"/>
                    <Edge fillStyle0="1" fillStyle1="2" edges="
!-318 -162[-330 -121 -331 -94!-331 -94|-312 -107!-312 -107|-300 -113!-300 -113|-299 -119!-299 -119[-292 -202 -279 -247!-279 -247[-299 -217 -312 -178!-312 -178|-314 -167!-314 -167|-318 -162!-266 -31|-259 57!-259 57[-257 72 -262 70!-262
 70[-266 71 -271 57!-271 57|-298 -31!-298 -31|-296 -41!-296 -41|-285 -46!-285 -46|-272 -41!-272 -41|-266 -31!-335 -64[-365 -36 -373 22!-373 22|-368 24!-368 24|-298 78!-298 78[-289 86 -289 92!-289 92|-302 91!-302 91|-376 58!-376 58[-376
 98 -367 128!-367 128|-351 166!-351 166|-294 135!-294 135|-281 134!-281 134[-277 140 -285 148!-285 148|-331 198!-331 198[-290 252 -231 270!-231 270[-241 265 -241 257!-241 257|-249 170!-249 170[-249 156 -245 157!-245 157[-242 155 -236
 170!-236 170|-209 257!-209 257[-205 271 -222 273!-222 273[-139 295 -108 212!-108 212[-82 143 -103 65!-103 65[-116 15 -154 -24!-154 -24[-191 -62 -240 -78!-240 -78[-299 -97 -335 -64"/>
                    <Edge fillStyle0="3" fillStyle1="2" edges="
!-75 -175|-79 -183!-79 -183|-74 -191!-74 -191|-48 -189!-48 -189|-37 -176!-37 -176[-33 -164 -51 -163!-51 -163[-69 -161 -73 -172!-73 -172|-75 -175"/>
                    <Edge fillStyle0="1" fillStyle1="2" edges="
!-148 49|-151 58!-151 58|-214 92!-214 92[-224 96 -227 92!-227 92[-229 86 -222 79!-222 79|-174 26!-174 26|-165 24!-165 24|-153 34!-153 34[-148 42 -148 49!-129 204|-139 202!-139 202|-209 148!-209 148|-218 135!-218 135|-205 136!-205 136
|-129 170!-129 170[-117 175 -122 194!-122 194|-129 204!-356 347|-382 380!-382 380[-394 369 -413 363!-413 363|-400 324!-400 324[-376 331 -356 347!-318 360[-350 313 -402 300!-402 300[-456 286 -513 314!-513 314[-560 338 -581 390!-581 390
[-601 439 -593 493!-593 493[-589 523 -574 547!-574 547|-568 545!-568 545|-546 544!-546 544[-545 554 -559 567!-559 567[-541 587 -512 601!-512 601|-498 599!-498 599[-449 617 -403 607!-403 607[-359 597 -329 564!-329 564[-304 536 -295 496
!-295 496[-286 458 -291 419!-291 419[-299 389 -312 368!-312 368|-318 360!-307 471[-310 497 -322 518!-322 518|-359 498!-359 498[-350 481 -349 466!-349 466|-307 471!-349 435|-349 434!-349 434[-352 418 -362 403!-362 403|-326 381!-326 381
[-315 398 -308 427!-308 427|-349 435!-477 366|-493 328!-493 328|-445 318!-445 318|-444 359!-444 359|-460 361!-460 361|-477 366!-561 391[-550 368 -531 352!-531 352|-504 383!-504 383|-525 410!-525 410|-561 391!-575 433|-534 439!-534 439
|-533 471!-533 471|-533 474!-533 474|-574 483!-574 483|-575 433!-436 589|-485 582!-485 582|-471 542!-471 542|-437 546!-437 546|-436 589"/>
                    <Edge fillStyle0="4" fillStyle1="2" edges="
!-581 579[-672 619 -797 578!-797 578[-915 538 -983 456!-983 456[-1033 567 -956 652!-956 652[-920 692 -829 756!-829 756|-787 784!-787 784|-777 790!-777 790|-646 700!-646 700[-568 646 -532 614!-532 614|-581 579"/>
                    <Edge fillStyle0="1" fillStyle1="2" edges="
!-521 502|-498 527!-498 527|-524 561!-524 561|-557 524!-557 524|-521 502"/>
                    <Edge fillStyle0="4" fillStyle1="2" edges="
!-565 709[-550 717 -549 723!-549 723|-533 777!-533 777|-478 782!-478 782[-434 791 -398 811!-398 811[-440 744 -454 684!-454 684|-459 652!-459 652|-527 642!-527 642|-599 697!-599 697|-565 709!-636 945[-861 1022 -917 1090!-917 1090|-920
 1093!-920 1093|-1277 1139!-1277 1139|-1241 1270!-1241 1270|-1223 1320!-1223 1320|-848 1346!-848 1346[-832 1347 -778 1314!-778 1314|-831 1298!-831 1298|-834 1298!-834 1298|-833 1297!-833 1297[-901 1263 -892 1199!-892 1199[-888 1168 -852
 1132!-852 1132|-792 1079!-792 1079[-736 1029 -631 959!-631 959|-636 945"/>
                    <Edge fillStyle0="1" fillStyle1="2" edges="
!-790 828[-788 851 -814 862!-814 862|-816 864!-816 864[-835 870 -855 864!-855 864[-877 858 -888 843!-888 843[-897 831 -893 817!-893 817|-876 795!-876 795|-971 724!-971 724[-1044 760 -1275 881!-1275 881[-1306 897 -1309 903!-1309 903|-1309
 944!-1309 944[-1305 1026 -1282 1119!-1282 1119|-930 1074!-930 1074[-882 1019 -730 959!-730 959[-637 921 -524 889!-524 889|-517 887!-517 887|-516 887!-516 887|-557 810!-557 810|-574 764!-574 764[-585 728 -579 729!-579 729|-624 715!-624
 715|-784 824!-784 824|-790 828!-592 973[-555 1057 -473 1148!-473 1148|-417 1042!-417 1042[-429 1037 -429 1032!-429 1032[-428 1010 -437 988!-437 988[-456 937 -526 930!-526 930|-592 973"/>
                    <Edge fillStyle1="2" edges="
!-585 928|-617 939!-617 939|-607 943!-607 943|-585 928"/>
                    <Edge fillStyle0="4" fillStyle1="2" edges="
!-479 902|-511 921!-511 921[-416 943 -396 1004!-396 1004|-355 931!-355 931|-348 924!-348 924[-365 822 -497 794!-497 794|-527 793!-527 793|-476 890!-476 890[-471 896 -479 902"/>
                    <Edge fillStyle0="1" fillStyle1="2" edges="
!-350 554|-392 580!-392 580|-407 540!-407 540|-378 522!-378 522|-350 554"/>
                    <Edge fillStyle1="2" edges="
!-292 939|-311 920!-311 920|-312 922!-312 922|-308 955!-308 955|-292 939"/>
                    <Edge fillStyle0="3" fillStyle1="2" edges="
!-1543 926[-1604 934 -1662 953!-1662 953[-1713 972 -1740 1002!-1740 1002|-1745 1010!-1745 1010[-1752 1025 -1734 1043!-1734 1043|-1701 1063!-1701 1063[-1665 1079 -1621 1079!-1621 1079[-1576 1079 -1540 1065!-1540 1065|-1524 1056!-1524 1056
|-1522 1053!-1522 1053[-1527 1053 -1527 1056!-1527 1056[-1532 1021 -1557 1003!-1557 1003[-1574 990 -1595 997!-1595 997[-1602 1000 -1599 978!-1599 978[-1596 955 -1587 952!-1587 952|-1549 954!-1549 954|-1543 926!-1521 976[-1511 999 -1465
 1042!-1465 1042[-1439 1067 -1400 1079!-1400 1079[-1357 1091 -1352 1064!-1352 1064[-1350 1048 -1361 1025!-1361 1025[-1364 1016 -1356 997!-1356 997|-1345 981!-1345 981|-1344 983!-1344 983|-1348 940!-1348 940[-1351 906 -1346 893!-1346 893
|-1379 879!-1379 879|-1415 873!-1415 873|-1434 873!-1434 873|-1471 881!-1471 881[-1489 888 -1503 903!-1503 903[-1518 918 -1523 936!-1523 936[-1528 957 -1521 976"/>
                    <Edge fillStyle0="1" fillStyle1="2" edges="
!-853 845|-850 849!-850 849|-848 848!-848 848[-832 842 -829 824!-829 824|-847 813!-847 813|-856 831!-856 831|-853 845"/>
                    <Edge fillStyle0="4" fillStyle1="2" edges="
!-992 1185[-996 1194 -1006 1199!-1006 1199|-1008 1201!-1008 1201[-1022 1205 -1038 1201!-1038 1201|-1065 1186!-1065 1186[-1074 1176 -1069 1165!-1069 1165[-1064 1155 -1052 1150!-1052 1150[-1040 1145 -1022 1150!-1022 1150[-1005 1155 -996
 1165!-996 1165[-988 1174 -992 1185!-1200 1218|-1227 1202!-1227 1202[-1235 1193 -1230 1182!-1230 1182[-1226 1172 -1214 1167!-1214 1167|-1184 1166!-1184 1166[-1166 1171 -1157 1182!-1157 1182[-1149 1191 -1153 1201!-1153 1201|-1167 1216
!-1167 1216|-1170 1218!-1170 1218[-1184 1222 -1200 1218"/>
                    <Edge fillStyle0="1" fillStyle1="2" edges="
!-831 1261[-714 1252 -611 1223!-611 1223[-704 1181 -754 1095!-754 1095[-884 1216 -842 1266!-842 1266|-831 1261!-1357 1229[-1360 1286 -1393 1322!-1393 1322[-1332 1325 -1275 1286!-1275 1286[-1312 1185 -1332 1069!-1332 1069[-1339 1121 -1386
 1130!-1386 1130|-1419 1127!-1419 1127|-1419 1141!-1419 1141|-1421 1155!-1421 1155|-1421 1158!-1421 1158[-1389 1155 -1371 1177!-1371 1177[-1355 1197 -1357 1229"/>
                    <Edge fillStyle0="3" fillStyle1="2" edges="
!-1554 1220[-1484 1213 -1446 1176!-1446 1176|-1439 1168!-1439 1168|-1437 1161!-1437 1161|-1433 1147!-1433 1147[-1436 1126 -1473 1111!-1473 1111[-1505 1097 -1527 1098!-1527 1098[-1557 1125 -1617 1126!-1617 1126[-1667 1126 -1711 1110!-1711
 1110[-1729 1119 -1736 1136!-1736 1136[-1740 1153 -1730 1172!-1730 1172[-1719 1191 -1700 1201!-1700 1201|-1673 1212!-1673 1212|-1611 1222!-1611 1222|-1579 1222!-1579 1222|-1570 1221!-1570 1221|-1568 1221!-1568 1221|-1554 1220!-1436 1196
[-1468 1250 -1550 1264!-1550 1264|-1552 1264!-1552 1264|-1643 1268!-1643 1268[-1612 1328 -1545 1332!-1545 1332[-1498 1335 -1444 1314!-1444 1314|-1439 1312!-1439 1312[-1407 1297 -1394 1286!-1394 1286[-1361 1259 -1381 1229!-1381 1229[-1399
 1202 -1433 1205!-1433 1205|-1436 1196!155 1062|148 1026!148 1026[140 1005 120 1006!120 1006|7 1029!7 1029[-45 1040 -35 1084!-35 1084|-22 1122!-22 1122[-11 1136 14 1131!14 1131[24 1129 39 1138!39 1138[54 1147 41 1154!41 1154[10 1170 33
 1168!33 1168|70 1161!70 1161|102 1154!102 1154|118 1147!118 1147[133 1138 121 1137!121 1137|102 1126!102 1126[94 1115 108 1112!108 1112[163 1099 155 1062"/>
                    <Edge fillStyle0="4" fillStyle1="2" edges="
!501 1335[474 1308 484 1272!484 1272|490 1257!490 1257|445 1269!445 1269|368 1279!368 1279[313 1280 293 1258!293 1258|289 1282!289 1282[289 1285 283 1285!283 1285|102 1317!102 1317|84 1315!84 1315|70 1305!70 1305|10 1191!10 1191[-10 1180
 -8 1160!-8 1160[-36 1158 -54 1138!-54 1138[-67 1124 -73 1098!-73 1098[-79 1073 -74 1051!-74 1051|-118 1071!-118 1071[-120 1212 -106 1353!-106 1353|-90 1389!-90 1389[-73 1431 -30 1495!-30 1495[20 1568 63 1607!63 1607|68 1610!68 1610[58
 1587 56 1551!56 1551[54 1487 98 1466!98 1466[132 1450 201 1459!201 1459|242 1481!242 1481[266 1498 284 1495!284 1495|434 1469!434 1469|509 1452!509 1452[553 1443 579 1459!579 1459|610 1441!610 1441[592 1430 585 1414!585 1414|527 1435
!527 1435|475 1445!475 1445[388 1459 307 1449!307 1449[254 1442 243 1417!243 1417|244 1404!244 1404[247 1395 250 1403!250 1403[261 1431 329 1434!329 1434|420 1431!420 1431[478 1428 537 1411!537 1411|579 1396!579 1396[577 1378 580 1363
!580 1363[551 1366 523 1351!523 1351|470 1361!470 1361[388 1376 302 1365!302 1365[249 1358 238 1333!238 1333|239 1320!239 1320[242 1312 245 1319!245 1319[256 1347 324 1351!324 1351|415 1347!415 1347|501 1335"/>
                    <Edge fillStyle0="1" fillStyle1="2" edges="
!230 1674|191 1665!191 1665|163 1669!163 1669[123 1673 96 1651!96 1651[49 1634 -4 1582!-4 1582[-44 1542 -87 1463!-87 1463[-125 1395 -151 1325!-151 1325[-168 1280 -228 1241!-228 1241[-276 1209 -337 1189!-337 1189[-356 1328 -363 1519!-363
 1519|-371 1849!-371 1849|-370 1872!-370 1872|-372 1894!-372 1894|-395 1949!-395 1949|-402 1944!-402 1944|-400 1946!-400 1946|-213 2107!-213 2107|-184 2103!-184 2103[-127 2040 -40 2018!-40 2018[50 1995 117 2033!117 2033|119 2034!119 2034
[160 2059 182 2100!182 2100|242 2042!242 2042|243 1986!243 1986|245 1983!245 1983[238 1971 242 1957!242 1957|290 1795!290 1795|236 1685!236 1685|230 1674!-497 1153[-579 1063 -616 990!-616 990|-734 1077!-734 1077|-728 1082!-728 1082|-716
 1105!-716 1105|-580 1213!-580 1213|-501 1183!-501 1183|-480 1160!-480 1160|-497 1153"/>
                    <Edge fillStyle0="4" edges="
!-770 1947|-773 1955!-773 1955[-773 2030 -681 2159!-681 2159[-591 2285 -507 2336!-507 2336|-500 2333!-500 2333[-497 2331 -497 2324!-497 2324[-497 2312 -562 2252!-562 2252[-641 2180 -672 2138!-672 2138[-696 2103 -722 2038!-722 2038[-750
 1966 -763 1944!-763 1944|-770 1947"/>
                    <Edge fillStyle0="3" fillStyle1="2" edges="
!510 2259|283 1985!283 1985[300 2103 215 2194!215 2194[126 2291 11 2247!11 2247[-32 2229 -43 2220!-43 2220|-71 2189!-71 2189[-90 2165 -100 2160!-100 2160|-155 2129!-155 2129|-158 2127!-158 2127|-160 2128!-160 2128|-425 2177!-425 2177
|-221 2419!-221 2419|-198 2428!-198 2428|79 2551!79 2551[84 2521 44 2477!44 2477|-18 2420!-18 2420[-76 2373 -143 2332!-143 2332[-155 2325 -133 2305!-133 2305[-111 2286 -100 2293!-100 2293[-30 2335 38 2391!38 2391[89 2435 109 2463!109
 2463[144 2515 118 2555!118 2555|108 2564!108 2564|234 2619!234 2619[425 2634 552 2732!552 2732|766 2388!766 2388|765 2388!765 2388|662 2277!662 2277|639 2252!639 2252|540 2269!540 2269[522 2272 510 2259"/>
                    <Edge fillStyle0="1" fillStyle1="2" edges="
!151 2186[163 2160 157 2129!157 2129[129 2058 62 2041!62 2041|16 2047!16 2047[-31 2065 -37 2115!-37 2115[-42 2160 -11 2197!-11 2197[38 2250 106 2226!106 2226[137 2214 151 2186"/>
                    <Edge fillStyle0="4" fillStyle1="2" edges="
!-43 2100[-25 2060 13 2037!13 2037[-72 2045 -139 2109!-139 2109[-100 2123 -45 2185!-45 2185[-61 2143 -43 2100"/>
                    <Edge fillStyle0="4" edges="
!-781 2123[-781 2336 -288 2587!-288 2587|-278 2585!-278 2585|-275 2583!-275 2583|-274 2576!-274 2576[-329 2546 -397 2504!-397 2504[-535 2421 -604 2359!-604 2359[-660 2308 -710 2228!-710 2228|-779 2111!-779 2111|-781 2123"/>
                    <Edge fillStyle0="4" fillStyle1="2" edges="
!1648 486|1630 507!1630 507[1617 517 1606 517!1606 517|1375 506!1375 506|1284 506!1284 506|1194 499!1194 499|1186 505!1186 505|1186 564!1186 564|1250 565!1250 565|1260 567!1260 567[1269 569 1274 575!1274 575[1280 580 1276 585!1276 585
|1271 589!1271 589[1223 621 1202 665!1202 665[1175 721 1230 748!1230 748|1236 750!1236 750|1243 729!1243 729[1286 656 1336 620!1336 620[1397 576 1478 579!1478 579[1565 581 1618 639!1618 639[1657 683 1691 777!1691 777[1750 635 1681 420
!1681 420|1648 486"/>
                    <Edge fillStyle0="1" fillStyle1="2" edges="
!1663 817|1452 869!1452 869[1288 901 1216 880!1216 880|874 1036!874 1036[916 1162 976 1253!976 1253|982 1254!982 1254|1145 1234!1145 1234|1454 1191!1454 1191[1510 1181 1559 1134!1559 1134|1640 1039!1640 1039|1673 1003!1673 1003[1689 982
 1684 962!1684 962[1666 903 1663 817!1227 458|1326 466!1326 466|1429 467!1429 467|1614 475!1614 475[1660 376 1690 279!1690 279[1731 141 1599 58!1599 58[1522 190 1430 286!1430 286[1331 390 1246 414!1246 414|1227 458!961 357[959 373 964
 390!964 390|964 391!964 391|924 402!924 402[918 376 919 353!919 353|961 357!959 269|988 298!988 298[975 311 969 326!969 326|931 309!931 309[940 286 959 269!979 477[960 465 943 442!943 442|978 418!978 418|1002 442!1002 442|979 477!906
 405[925 449 961 482!961 482[999 516 1042 525!1042 525[1090 526 1133 497!1133 497[1177 468 1197 421!1197 421[1181 420 1204 397!1204 397[1214 358 1204 317!1204 317[1186 235 1105 214!1105 214[1027 192 962 242!962 242[926 269 912 315!912
 315[899 357 906 405!1164 286[1178 304 1186 330!1186 330|1145 341!1145 341|1144 339!1144 339|1131 310!1131 310|1164 286!1078 273|1088 233!1088 233[1112 239 1133 254!1133 254|1109 288!1109 288[1094 277 1078 273!1029 274|1013 280!1013 280
|995 243!995 243|1043 229!1043 229|1047 271!1047 271|1029 274!1064 457|1069 500!1069 500|1019 496!1019 496|1030 455!1030 455|1064 457!1094 449|1121 430!1121 430|1152 459!1152 459[1136 476 1111 488!1111 488|1094 449!1139 405|1148 372!1148
 372|1190 375!1190 375[1188 402 1177 423!1177 423|1139 405"/>
                    <Edge fillStyle0="4" fillStyle1="2" edges="
!1162 603[1141 611 1113 631!1113 631|878 797!878 797|824 837!824 837[819 846 833 900!833 900|867 1017!867 1017|1214 859!1214 859|1218 860!1218 860[1316 892 1597 814!1597 814[1414 816 1294 790!1294 790|1258 782!1258 782|1256 785!1256 785
|1243 778!1243 778[1183 759 1160 712!1160 712[1134 660 1208 594!1208 594|1162 603!892 899|899 899!899 899[934 897 948 917!948 917[955 928 949 938!949 938|932 952!932 952|901 950!901 950[883 945 876 933!876 933[869 924 873 914!873 914
|889 901!889 901[889 899 892 899!1038 837|1054 823!1054 823|1057 822!1057 822|1064 822!1064 822[1099 820 1113 840!1113 840[1120 851 1114 861!1114 861[1109 871 1096 875!1096 875|1066 874!1066 874|1040 857!1040 857[1034 847 1038 837"/>
                    <Edge fillStyle0="1" fillStyle1="2" edges="
!1596 681|1337 719!1337 719|1307 734!1307 734|1285 729!1285 729|1268 762!1268 762|1340 775!1340 775|1412 781!1412 781|1659 788!1659 788|1613 683!1613 683|1596 681!1584 632[1546 573 1410 612!1410 612[1347 630 1300 705!1300 705[1370 672
 1450 663!1450 663|1605 670!1605 670|1584 632!625 415[605 403 619 386!619 386[662 328 709 350!709 350[728 360 732 403!732 403|733 463!733 463[734 576 726 619!726 619[707 712 640 733!640 733[620 739 614 717!614 717[608 696 628 689!628
 689[668 677 680 618!680 618|687 522!687 522|688 437!688 437|683 399!683 399[676 384 658 408!658 408[645 426 625 415"/>
                    <Edge fillStyle0="3" fillStyle1="4" edges="
!364 89[369 117 366 139!366 139[363 161 353 163!353 163[342 165 331 146!331 146[319 127 314 99!314 99[308 71 311 49!311 49[314 27 325 25!325 25[335 23 347 42!347 42[358 60 364 89"/>
                    <Edge fillStyle0="3" fillStyle1="2" edges="
!527 967|525 997!525 997[524 1036 569 1038!569 1038|579 1042!579 1042|576 1043!576 1043|602 1037!602 1037|600 1018!600 1018[604 989 613 986!613 986[642 976 682 946!682 946|539 942!539 942[529 950 527 967!712 963|634 1018!634 1018|649
 1029!649 1029|649 1030!649 1030|704 1025!704 1025|707 1022!707 1022[776 983 763 1027!763 1027|824 1022!824 1022|801 945!801 945[757 934 712 963"/>
                    <Edge fillStyle0="1" fillStyle1="2" edges="
!139 982[179 994 192 1052!192 1052[203 1107 157 1128!157 1128[172 1143 160 1159!160 1159[151 1173 130 1179!130 1179|92 1186!92 1186|48 1196!48 1196|100 1295!100 1295|236 1272!236 1272[247 1270 270 1232!270 1232[296 1190 315 1177!315 1177
[371 1138 448 1148!448 1148[453 1126 473 1102!473 1102[491 1082 512 1069!512 1069|532 1058!532 1058[485 1043 486 999!486 999[488 962 495 943!495 943[298 946 139 982"/>
                    <Edge fillStyle0="3" fillStyle1="2" edges="
!630 1090[624 1111 639 1151!639 1151|704 1291!704 1291|749 1389!749 1389|759 1413!759 1413|771 1423!771 1423[839 1414 893 1369!893 1369[930 1329 954 1276!954 1276|949 1270!949 1270[882 1177 835 1052!835 1052|834 1053!834 1053|709 1072
!709 1072|665 1075!665 1075[633 1079 630 1090"/>
                    <Edge fillStyle0="4" fillStyle1="2" edges="
!495 1228|461 1201!461 1201[450 1189 447 1172!447 1172[399 1167 358 1185!358 1185[315 1204 298 1241!298 1241[316 1259 395 1256!395 1256[475 1251 504 1232!504 1232|495 1228"/>
                    <Edge fillStyle0="1" fillStyle1="2" edges="
!499 1176|525 1189!525 1189[540 1197 539 1210!539 1210[536 1236 520 1252!520 1252[490 1283 534 1304!534 1304[576 1324 609 1314!609 1314[617 1311 613 1333!613 1333|604 1358!604 1358[583 1378 631 1398!631 1398|718 1423!718 1423|611 1190
!611 1190[582 1128 617 1080!617 1080|563 1091!563 1091[542 1096 504 1114!504 1114[475 1129 476 1145!476 1145[476 1158 499 1176!649 1458|595 1490!595 1490[577 1500 564 1485!564 1485|559 1479!559 1479|427 1502!427 1502|356 1518!356 1518
|283 1527!283 1527[278 1554 279 1564!279 1564[283 1583 305 1584!305 1584|392 1577!392 1577|541 1552!541 1552|538 1561!538 1561|528 1571!528 1571|349 1600!349 1600|303 1606!303 1606|394 1827!394 1827[410 1861 436 1869!436 1869|499 1867
!499 1867|546 1859!546 1859[578 1850 582 1835!582 1835[587 1809 581 1766!581 1766[580 1759 596 1748!596 1748|599 1806!599 1806[597 1840 578 1858!578 1858[556 1879 500 1888!500 1888[447 1897 416 1889!416 1889[393 1883 371 1839!371 1839
|343 1761!343 1761|281 1606!281 1606|281 1603!281 1603|278 1602!278 1602[260 1595 262 1568!262 1568|270 1527!270 1527|270 1526!270 1526[237 1519 216 1501!216 1501[193 1484 110 1494!110 1494[87 1549 103 1605!103 1605|134 1641!134 1641
|136 1641!136 1641|231 1629!231 1629|246 1631!246 1631|256 1641!256 1641|297 1740!297 1740[327 1806 355 1849!355 1849[447 1994 556 1948!556 1948[665 1902 698 1792!698 1792[723 1711 708 1573!708 1573|709 1566!709 1566|716 1561!716 1561
|720 1559!720 1559|721 1559!721 1559|804 1551!804 1551[834 1548 848 1510!848 1510[861 1474 851 1438!851 1438[837 1447 819 1453!819 1453|826 1477!826 1477[830 1497 826 1512!826 1512[822 1527 813 1528!813 1528[805 1530 796 1516!796 1516
[788 1503 785 1483!785 1483|784 1464!784 1464|649 1458"/>
                    <Edge fillStyle0="4" fillStyle1="2" edges="
!748 1588[770 1821 671 1920!671 1920|675 1926!675 1926|737 1868!737 1868[800 1808 839 1716!839 1716|900 1542!900 1542|903 1534!903 1534[956 1398 1141 1262!1141 1262|974 1281!974 1281|971 1281!971 1281[950 1325 921 1361!921 1361[919 1384
 913 1391!913 1391|881 1418!881 1418[906 1478 885 1527!885 1527[878 1548 859 1564!859 1564[840 1580 806 1584!806 1584|748 1588"/>
                    <Edge fillStyle0="1" fillStyle1="2" edges="
!1430 1020[1415 1025 1409 1041!1409 1041|1410 1055!1410 1055|1414 1063!1414 1063[1430 1059 1435 1042!1435 1042|1435 1027!1435 1027|1432 1022!1432 1022|1430 1020!1445 1078|1406 1076!1406 1076[1385 1069 1374 1054!1374 1054[1364 1040 1373
 1025!1373 1025[1381 1011 1397 1005!1397 1005|1400 1004!1400 1004|1407 1003!1407 1003[1450 999 1470 1028!1470 1028[1480 1043 1471 1059!1471 1059[1462 1074 1445 1078!1021 1426[945 1522 910 1641!910 1641[885 1727 849 1787!849 1787[812 1847
 747 1908!747 1908|624 2023!624 2023|736 2165!736 2165|849 2306!849 2306|886 2352!886 2352|858 2112!858 2112[857 2104 868 2104!868 2104|885 2107!885 2107|1029 2153!1029 2153[1119 2182 1168 2212!1168 2212[1196 2229 1211 2286!1211 2286
|1221 2259!1221 2259[1256 2173 1359 2159!1359 2159[1440 2147 1543 2181!1543 2181|1466 2022!1466 2022|1442 2015!1442 2015|1410 2001!1410 2001[1390 1986 1375 1919!1375 1919|1357 1827!1357 1827|1199 1264!1199 1264[1089 1342 1021 1426"/>
                    <Edge fillStyle0="4" fillStyle1="2" edges="
!1567 2218[1515 2196 1469 2188!1469 2188[1498 2209 1510 2243!1510 2243[1523 2279 1511 2312!1511 2312[1496 2354 1464 2378!1464 2378[1431 2403 1388 2402!1388 2402[1305 2391 1293 2316!1293 2316[1281 2245 1336 2198!1336 2198[1308 2210 1285
 2232!1285 2232[1234 2280 1236 2382!1236 2382[1262 2432 1321 2451!1321 2451|1436 2447!1436 2447[1469 2433 1515 2385!1515 2385[1587 2313 1581 2231!1581 2231|1579 2220!1579 2220|1567 2218"/>
                    <Edge fillStyle0="1" fillStyle1="2" edges="
!1324 2225[1295 2266 1310 2313!1310 2313[1319 2342 1345 2361!1345 2361[1369 2378 1400 2382!1400 2382[1499 2384 1497 2293!1497 2293[1495 2202 1404 2190!1404 2190[1354 2183 1324 2225"/>
                    <Edge fillStyle0="3" fillStyle1="2" edges="
!1530 2421[1489 2456 1442 2475!1442 2475[1381 2499 1314 2473!1314 2473[1253 2449 1210 2396!1210 2396[1192 2373 1179 2324!1179 2324[1166 2268 1154 2248!1154 2248|1137 2222!1137 2222|1101 2208!1101 2208|899 2133!899 2133|919 2330!919 2330
[934 2467 952 2492!952 2492|1042 2609!1042 2609|1137 2722!1137 2722|1145 2717!1145 2717[1176 2701 1113 2536!1113 2536|1061 2424!1061 2424[1055 2412 1080 2395!1080 2395[1105 2378 1110 2389!1110 2389[1173 2507 1190 2570!1190 2570[1226 2697
 1153 2741!1153 2741|1240 2854!1240 2854[1326 2894 1393 2951!1393 2951[1468 3015 1508 3090!1508 3090[1563 3070 1652 3019!1652 3019|1792 2940!1792 2940|1806 2933!1806 2933|1802 2918!1802 2918|1766 2752!1766 2752|1765 2740!1765 2740|1664
 2701!1664 2701|1652 2691!1652 2691|1597 2338!1597 2338[1574 2383 1530 2421"/>
                    <Edge fillStyle0="1" fillStyle1="2" edges="
!924 2951|918 3002!918 3002|825 2991!825 2991[817 3011 816 3030!816 3030|815 3036!815 3036|912 3047!912 3047|906 3098!906 3098|809 3086!809 3086|803 3132!803 3132|901 3143!901 3143|895 3194!895 3194|796 3182!796 3182|783 3285!783 3285
|1478 3099!1478 3099|1477 3098!1477 3098[1440 3025 1368 2962!1368 2962[1303 2905 1221 2867!1221 2867|1102 2842!1102 2842|981 2828!981 2828[899 2845 846 2942!846 2942|924 2951"/>
                    <Edge fillStyle0="4" fillStyle1="2" edges="
!173 2143[167 2181 139 2214!139 2214|124 2228!124 2228[187 2192 223 2112!223 2112|195 2139!195 2139[187 2147 173 2143"/>
                    <Edge fillStyle0="1" fillStyle1="2" edges="
!94 2947|28 3020!28 3020|58 3056!58 3056|128 2978!128 2978|166 3012!166 3012|95 3091!95 3091|129 3122!129 3122|200 3043!200 3043|238 3078!238 3078|166 3157!166 3157|242 3227!242 3227|539 2751!539 2751|538 2750!538 2750[423 2654 240 2640
!240 2640[129 2698 108 2711!108 2711[32 2756 -6 2803!-6 2803[-40 2878 2 2973!2 2973|56 2913!56 2913|94 2947"/>
                    <Edge fillStyle0="4" edges="
!2318 2644|2255 2775!2255 2775[2231 2819 2148 2889!2148 2889|2008 2998!2008 2998|2010 3004!2010 3004[2012 3008 2018 3008!2018 3008[2059 3008 2153 2920!2153 2920|2255 2811!2255 2811[2292 2762 2321 2709!2321 2709[2362 2636 2362 2597!2362
 2597[2362 2552 2318 2644!2168 2688|2125 2766!2125 2766[2072 2849 2025 2899!2025 2899[1894 3038 1703 3121!1703 3121|1708 3130!1708 3130|1721 3133!1721 3133[1767 3133 1893 3039!1893 3039[1989 2968 2034 2923!2034 2923[2064 2893 2123 2808
!2123 2808[2194 2706 2194 2672!2194 2672[2194 2642 2168 2688"/>
                  </edges>
                </DOMShape>
              </elements>
            </DOMFrame>
          </frames>
        </DOMLayer>
      </layers>
    </DOMTimeline>
  </timeline>
</DOMSymbolItem>